{
  "data": {
    "article": {},
    "attachments": {},
    "author_id": "1741993395910811648",
    "conversation_id": "1901523188401463301",
    "created_at": "2025-03-17T07:32:53.000Z",
    "edit_controls": {
      "edits_remaining": 5,
      "is_edit_eligible": false,
      "editable_until": "2025-03-17T08:32:53.000Z"
    },
    "edit_history_tweet_ids": [
      "1901537207699255706"
    ],
    "entities": {
      "mentions": [
        {
          "start": 0,
          "end": 10,
          "username": "nejamais1",
          "id": "1347140950095613953"
        }
      ]
    },
    "geo": {},
    "id": "1901537207699255706",
    "in_reply_to_user_id": "1347140950095613953",
    "lang": "qme",
    "note_tweet": {
      "entities": {}
    },
    "possibly_sensitive": false,
    "public_metrics": {
      "retweet_count": 0,
      "reply_count": 0,
      "like_count": 0,
      "quote_count": 0,
      "bookmark_count": 0,
      "impression_count": 0
    },
    "referenced_tweets": [
      {
        "type": "replied_to",
        "id": "1901532646053998798"
      }
    ],
    "reply_settings": "everyone",
    "text": "@nejamais1 🥰🥰"
  },
  "includes": {
    "users": [
      {
        "created_at": "2024-01-02T01:22:57.000Z",
        "description": "互fo欢迎！ 猫，诗歌，精神动力学。艺术，C#，波粒二象性。回归曲线上的量子生物，无攻击性。“我们彻夜飞旋，直至没入火焰。”阴暗碎碎念纯享版@TauCeti_10700 提问箱👇",
        "entities": {
          "url": {
            "urls": [
              {
                "start": 0,
                "end": 23,
                "url": "https://t.co/MuEKSg4tIS",
                "expanded_url": "https://ngl.link/anincandescence",
                "display_url": "ngl.link/anincandescence"
              }
            ]
          },
          "description": {
            "mentions": [
              {
                "start": 70,
                "end": 84,
                "username": "TauCeti_10700"
              }
            ]
          }
        },
        "id": "1741993395910811648",
        "location": "0°00′N 260°00′E Mars",
        "name": "炽烈已极",
        "pinned_tweet_id": "1896009323920404722",
        "profile_image_url": "https://pbs.twimg.com/profile_images/1789433740277567488/d3KhwUX1_normal.jpg",
        "protected": false,
        "public_metrics": {
          "followers_count": 325,
          "following_count": 164,
          "tweet_count": 1739,
          "listed_count": 1,
          "like_count": 5033,
          "media_count": 412
        },
        "url": "https://t.co/MuEKSg4tIS",
        "username": "AnIncandescence",
        "verified": false
      },
      {
        "created_at": "2021-01-07T11:22:13.000Z",
        "description": "男的/可以叫我小天/温良恭俭让/上一条是o大了胡扯的",
        "id": "1347140950095613953",
        "name": "Polarstern",
        "pinned_tweet_id": "1895562422930587880",
        "profile_image_url": "https://pbs.twimg.com/profile_images/1896590731726528512/1xlvoAx9_normal.jpg",
        "protected": false,
        "public_metrics": {
          "followers_count": 135,
          "following_count": 370,
          "tweet_count": 3163,
          "listed_count": 1,
          "like_count": 3379,
          "media_count": 157
        },
        "username": "nejamais1",
        "verified": false
      }
    ],
    "tweets": [
      {
        "article": {},
        "attachments": {},
        "author_id": "1741993395910811648",
        "conversation_id": "1901523188401463301",
        "created_at": "2025-03-17T07:32:53.000Z",
        "edit_controls": {
          "edits_remaining": 5,
          "is_edit_eligible": false,
          "editable_until": "2025-03-17T08:32:53.000Z"
        },
        "edit_history_tweet_ids": [
          "1901537207699255706"
        ],
        "entities": {
          "mentions": [
            {
              "start": 0,
              "end": 10,
              "username": "nejamais1",
              "id": "1347140950095613953"
            }
          ]
        },
        "geo": {},
        "id": "1901537207699255706",
        "in_reply_to_user_id": "1347140950095613953",
        "lang": "qme",
        "note_tweet": {
          "entities": {}
        },
        "possibly_sensitive": false,
        "public_metrics": {
          "retweet_count": 0,
          "reply_count": 0,
          "like_count": 0,
          "quote_count": 0,
          "bookmark_count": 0,
          "impression_count": 0
        },
        "referenced_tweets": [
          {
            "type": "replied_to",
            "id": "1901532646053998798"
          }
        ],
        "reply_settings": "everyone",
        "text": "@nejamais1 🥰🥰"
      },
      {
        "article": {},
        "attachments": {},
        "author_id": "1347140950095613953",
        "conversation_id": "1901523188401463301",
        "created_at": "2025-03-17T07:14:46.000Z",
        "edit_controls": {
          "edits_remaining": 5,
          "is_edit_eligible": false,
          "editable_until": "2025-03-17T08:14:46.000Z"
        },
        "edit_history_tweet_ids": [
          "1901532646053998798"
        ],
        "entities": {
          "mentions": [
            {
              "start": 0,
              "end": 16,
              "username": "AnIncandescence",
              "id": "1741993395910811648"
            }
          ]
        },
        "geo": {},
        "id": "1901532646053998798",
        "in_reply_to_user_id": "1741993395910811648",
        "lang": "zh",
        "note_tweet": {
          "entities": {}
        },
        "possibly_sensitive": false,
        "public_metrics": {
          "retweet_count": 0,
          "reply_count": 1,
          "like_count": 1,
          "quote_count": 0,
          "bookmark_count": 0,
          "impression_count": 8
        },
        "referenced_tweets": [
          {
            "type": "replied_to",
            "id": "1901523188401463301"
          }
        ],
        "reply_settings": "everyone",
        "text": "@AnIncandescence 这简直是仙品！"
      }
    ]
  },
  "_pale_fire": {
    "x_api_reply_chains": {
      "1901523188401463301": {
        "version": 1,
        "fetched_at": "2026-04-18T00:05:29Z",
        "max_depth": 63,
        "posts": [
          {
            "id": "1901523188401463301",
            "source": "local_json",
            "payload": {
              "data": {
                "article": {},
                "attachments": {
                  "media_keys": [
                    "3_1901523162820730880",
                    "3_1901523162824925185",
                    "3_1901523163198205953"
                  ]
                },
                "author_id": "1741993395910811648",
                "conversation_id": "1901523188401463301",
                "created_at": "2025-03-17T06:37:11.000Z",
                "edit_controls": {
                  "edits_remaining": 5,
                  "is_edit_eligible": true,
                  "editable_until": "2025-03-17T07:37:11.000Z"
                },
                "edit_history_tweet_ids": [
                  "1901523188401463301"
                ],
                "entities": {
                  "urls": [
                    {
                      "start": 11,
                      "end": 34,
                      "url": "https://t.co/nkc3VmNj6o",
                      "expanded_url": "https://x.com/AnIncandescence/status/1901523188401463301/photo/1",
                      "display_url": "pic.x.com/nkc3VmNj6o",
                      "media_key": "3_1901523162820730880"
                    },
                    {
                      "start": 11,
                      "end": 34,
                      "url": "https://t.co/nkc3VmNj6o",
                      "expanded_url": "https://x.com/AnIncandescence/status/1901523188401463301/photo/1",
                      "display_url": "pic.x.com/nkc3VmNj6o",
                      "media_key": "3_1901523162824925185"
                    },
                    {
                      "start": 11,
                      "end": 34,
                      "url": "https://t.co/nkc3VmNj6o",
                      "expanded_url": "https://x.com/AnIncandescence/status/1901523188401463301/photo/1",
                      "display_url": "pic.x.com/nkc3VmNj6o",
                      "media_key": "3_1901523163198205953"
                    }
                  ]
                },
                "geo": {},
                "id": "1901523188401463301",
                "lang": "zh",
                "note_tweet": {
                  "entities": {}
                },
                "possibly_sensitive": false,
                "public_metrics": {
                  "retweet_count": 0,
                  "reply_count": 0,
                  "like_count": 0,
                  "quote_count": 0,
                  "bookmark_count": 0,
                  "impression_count": 0
                },
                "reply_settings": "everyone",
                "text": "完工！进行一个画的摆 https://t.co/nkc3VmNj6o"
              },
              "includes": {
                "media": [
                  {
                    "height": 3024,
                    "media_key": "3_1901523162820730880",
                    "public_metrics": {},
                    "type": "photo",
                    "url": "https://pbs.twimg.com/media/GmORPewbYAA2oOy.jpg",
                    "width": 4032
                  },
                  {
                    "height": 4032,
                    "media_key": "3_1901523162824925185",
                    "public_metrics": {},
                    "type": "photo",
                    "url": "https://pbs.twimg.com/media/GmORPexbYAEiAt0.jpg",
                    "width": 3024
                  },
                  {
                    "height": 3024,
                    "media_key": "3_1901523163198205953",
                    "public_metrics": {},
                    "type": "photo",
                    "url": "https://pbs.twimg.com/media/GmORPgKbMAEUhiB.jpg",
                    "width": 4032
                  }
                ],
                "users": [
                  {
                    "created_at": "2024-01-02T01:22:57.000Z",
                    "description": "互fo欢迎！ 猫，诗歌，精神动力学。艺术，C#，波粒二象性。回归曲线上的量子生物，无攻击性。“我们彻夜飞旋，直至没入火焰。”阴暗碎碎念纯享版@TauCeti_10700 提问箱👇",
                    "entities": {
                      "url": {
                        "urls": [
                          {
                            "start": 0,
                            "end": 23,
                            "url": "https://t.co/MuEKSg4tIS",
                            "expanded_url": "https://ngl.link/anincandescence",
                            "display_url": "ngl.link/anincandescence"
                          }
                        ]
                      },
                      "description": {
                        "mentions": [
                          {
                            "start": 70,
                            "end": 84,
                            "username": "TauCeti_10700"
                          }
                        ]
                      }
                    },
                    "id": "1741993395910811648",
                    "location": "0°00′N 260°00′E Mars",
                    "name": "炽烈已极",
                    "pinned_tweet_id": "1896009323920404722",
                    "profile_image_url": "https://pbs.twimg.com/profile_images/1789433740277567488/d3KhwUX1_normal.jpg",
                    "protected": false,
                    "public_metrics": {
                      "followers_count": 325,
                      "following_count": 164,
                      "tweet_count": 1738,
                      "listed_count": 1,
                      "like_count": 5031,
                      "media_count": 412
                    },
                    "url": "https://t.co/MuEKSg4tIS",
                    "username": "AnIncandescence",
                    "verified": false
                  }
                ],
                "tweets": [
                  {
                    "article": {},
                    "attachments": {
                      "media_keys": [
                        "3_1901523162820730880",
                        "3_1901523162824925185",
                        "3_1901523163198205953"
                      ]
                    },
                    "author_id": "1741993395910811648",
                    "conversation_id": "1901523188401463301",
                    "created_at": "2025-03-17T06:37:11.000Z",
                    "edit_controls": {
                      "edits_remaining": 5,
                      "is_edit_eligible": true,
                      "editable_until": "2025-03-17T07:37:11.000Z"
                    },
                    "edit_history_tweet_ids": [
                      "1901523188401463301"
                    ],
                    "entities": {
                      "urls": [
                        {
                          "start": 11,
                          "end": 34,
                          "url": "https://t.co/nkc3VmNj6o",
                          "expanded_url": "https://x.com/AnIncandescence/status/1901523188401463301/photo/1",
                          "display_url": "pic.x.com/nkc3VmNj6o",
                          "media_key": "3_1901523162820730880"
                        },
                        {
                          "start": 11,
                          "end": 34,
                          "url": "https://t.co/nkc3VmNj6o",
                          "expanded_url": "https://x.com/AnIncandescence/status/1901523188401463301/photo/1",
                          "display_url": "pic.x.com/nkc3VmNj6o",
                          "media_key": "3_1901523162824925185"
                        },
                        {
                          "start": 11,
                          "end": 34,
                          "url": "https://t.co/nkc3VmNj6o",
                          "expanded_url": "https://x.com/AnIncandescence/status/1901523188401463301/photo/1",
                          "display_url": "pic.x.com/nkc3VmNj6o",
                          "media_key": "3_1901523163198205953"
                        }
                      ]
                    },
                    "geo": {},
                    "id": "1901523188401463301",
                    "lang": "zh",
                    "note_tweet": {
                      "entities": {}
                    },
                    "possibly_sensitive": false,
                    "public_metrics": {
                      "retweet_count": 0,
                      "reply_count": 0,
                      "like_count": 0,
                      "quote_count": 0,
                      "bookmark_count": 0,
                      "impression_count": 0
                    },
                    "reply_settings": "everyone",
                    "text": "完工！进行一个画的摆 https://t.co/nkc3VmNj6o"
                  }
                ]
              }
            }
          }
        ]
      }
    }
  }
}
