{"data":{"article":{},"attachments":{},"author_id":"1741993395910811648","conversation_id":"2025193865871859855","created_at":"2026-02-21T14:08:34.000Z","edit_controls":{"edits_remaining":5,"is_edit_eligible":false,"editable_until":"2026-02-21T15:08:34.000Z"},"edit_history_tweet_ids":["2025211044629791098"],"entities":{"mentions":[{"start":0,"end":16,"username":"sashiburi519534","id":"1695406391609966592"}]},"geo":{},"id":"2025211044629791098","in_reply_to_user_id":"1695406391609966592","lang":"zh","note_tweet":{"entities":{}},"possibly_sensitive":false,"public_metrics":{"retweet_count":0,"reply_count":0,"like_count":0,"quote_count":0,"bookmark_count":0,"impression_count":0},"referenced_tweets":[{"type":"replied_to","id":"2025193865871859855"}],"reply_settings":"everyone","text":"@sashiburi519534 寂静的春天…"},"includes":{"users":[{"created_at":"2024-01-02T01:22:57.000Z","description":"猫，诗歌，精神动力学。艺术，朝闻道，波粒二象性。不断寻找着广播塔的星际候鸟。 | “我们彻夜飞旋，直至没入火焰。” | 倒影@TauCeti_10700 计划这个号机的浓度更高一些 | 🚪88/158","entities":{"url":{"urls":[{"start":0,"end":23,"url":"https://t.co/iO6MRJNTYR","expanded_url":"https://ngl.link/anincandescence1","display_url":"ngl.link/anincandescenc…"}]},"description":{"mentions":[{"start":62,"end":76,"username":"TauCeti_10700"}]}},"id":"1741993395910811648","location":"天鹅座X-1 //⬇️ 匿名提问箱","name":"炽烈已极","pinned_tweet_id":"2024076888923365667","profile_image_url":"https://pbs.twimg.com/profile_images/2006317223414255617/jGT_GZyG_normal.jpg","protected":false,"public_metrics":{"followers_count":1723,"following_count":233,"tweet_count":5829,"listed_count":5,"like_count":14130,"media_count":1057},"url":"https://t.co/iO6MRJNTYR","username":"AnIncandescence","verified":false},{"created_at":"2023-08-26T12:03:04.000Z","description":"我是叉子/玩很多ns游戏/喜欢开心果味/不是DJ小女孩/麸质过敏/hazy ipa/烤鸭/裸睡/大蒜酱/喜欢水水獭/喜欢橘子/不爱吃饭很瘦/怕冷怕热/讨厌蚊子/喜欢蟑螂/《爱蠊说/葱花好吃/喫煙/会骑自行车/不吃韭菜/死了已经/Shoegaze/ NGL https://t.co/DyGKzxrd0I","entities":{"description":{"urls":[{"start":128,"end":151,"url":"https://t.co/DyGKzxrd0I","expanded_url":"http://ngl.link/sashiburi5195342","display_url":"ngl.link/sashiburi51953…"}]}},"id":"1695406391609966592","location":"Sintra, Portugal","name":"怒羅衛門","pinned_tweet_id":"1872574195990974933","profile_image_url":"https://pbs.twimg.com/profile_images/1801746828297117696/ht4Uakoe_normal.jpg","protected":false,"public_metrics":{"followers_count":302,"following_count":1078,"tweet_count":7013,"listed_count":3,"like_count":19993,"media_count":1384},"username":"sashiburi519534","verified":false}],"tweets":[{"article":{},"attachments":{},"author_id":"1741993395910811648","conversation_id":"2025193865871859855","created_at":"2026-02-21T14:08:34.000Z","edit_controls":{"edits_remaining":5,"is_edit_eligible":false,"editable_until":"2026-02-21T15:08:34.000Z"},"edit_history_tweet_ids":["2025211044629791098"],"entities":{"mentions":[{"start":0,"end":16,"username":"sashiburi519534","id":"1695406391609966592"}]},"geo":{},"id":"2025211044629791098","in_reply_to_user_id":"1695406391609966592","lang":"zh","note_tweet":{"entities":{}},"possibly_sensitive":false,"public_metrics":{"retweet_count":0,"reply_count":0,"like_count":0,"quote_count":0,"bookmark_count":0,"impression_count":0},"referenced_tweets":[{"type":"replied_to","id":"2025193865871859855"}],"reply_settings":"everyone","text":"@sashiburi519534 寂静的春天…"},{"article":{},"attachments":{},"author_id":"1695406391609966592","conversation_id":"2025193865871859855","created_at":"2026-02-21T13:00:18.000Z","edit_controls":{"edits_remaining":5,"is_edit_eligible":true,"editable_until":"2026-02-21T14:00:18.000Z"},"edit_history_tweet_ids":["2025193865871859855"],"entities":{},"geo":{},"id":"2025193865871859855","lang":"zh","note_tweet":{"entities":{}},"possibly_sensitive":false,"public_metrics":{"retweet_count":0,"reply_count":3,"like_count":19,"quote_count":0,"bookmark_count":0,"impression_count":644},"reply_settings":"everyone","text":"昨晚看到一位住的不远的互关应该是自杀了\n\n发了消息也没有回我\n\n我们互动并不多\n也没有说过很多几句话\n\n希望是喝多了没醒酒吧"}]}}
