{
  "data": {
    "article": {},
    "attachments": {},
    "author_id": "1741993395910811648",
    "conversation_id": "2017353644375474297",
    "created_at": "2026-01-31T09:58:43.000Z",
    "edit_controls": {
      "edits_remaining": 5,
      "is_edit_eligible": false,
      "editable_until": "2026-01-31T10:58:43.000Z"
    },
    "edit_history_tweet_ids": [
      "2017538021843997118"
    ],
    "entities": {
      "mentions": [
        {
          "start": 0,
          "end": 15,
          "username": "Jessie_Tianjia",
          "id": "2762638401"
        },
        {
          "start": 16,
          "end": 30,
          "username": "copper1234000",
          "id": "1983727547142828035"
        }
      ]
    },
    "geo": {},
    "id": "2017538021843997118",
    "in_reply_to_user_id": "2762638401",
    "lang": "zh",
    "note_tweet": {
      "entities": {}
    },
    "possibly_sensitive": false,
    "public_metrics": {
      "retweet_count": 0,
      "reply_count": 0,
      "like_count": 0,
      "quote_count": 0,
      "bookmark_count": 0,
      "impression_count": 0
    },
    "referenced_tweets": [
      {
        "type": "replied_to",
        "id": "2017378723448631405"
      }
    ],
    "reply_settings": "everyone",
    "text": "@Jessie_Tianjia @copper1234000 啊它开车还需要提示词吗（）"
  },
  "includes": {
    "users": [
      {
        "created_at": "2024-01-02T01:22:57.000Z",
        "description": "猫，诗歌，精神动力学。艺术，朝闻道，波粒二象性。不断寻找着广播塔的星际候鸟。 | “我们彻夜飞旋，直至没入火焰。” | 匿名提问箱⬇️ | @TauCeti_10700 日常和碎碎念 | 🚪88/158",
        "entities": {
          "url": {
            "urls": [
              {
                "start": 0,
                "end": 23,
                "url": "https://t.co/iO6MRJNTYR",
                "expanded_url": "https://ngl.link/anincandescence1",
                "display_url": "ngl.link/anincandescenc…"
              }
            ]
          },
          "description": {
            "mentions": [
              {
                "start": 70,
                "end": 84,
                "username": "TauCeti_10700"
              }
            ]
          }
        },
        "id": "1741993395910811648",
        "location": "天鹅座X-1",
        "name": "炽烈已极",
        "pinned_tweet_id": "2010452086539145687",
        "profile_image_url": "https://pbs.twimg.com/profile_images/2006317223414255617/jGT_GZyG_normal.jpg",
        "protected": false,
        "public_metrics": {
          "followers_count": 1552,
          "following_count": 224,
          "tweet_count": 5398,
          "listed_count": 6,
          "like_count": 13262,
          "media_count": 1015
        },
        "url": "https://t.co/iO6MRJNTYR",
        "username": "AnIncandescence",
        "verified": false
      },
      {
        "created_at": "2014-09-06T07:19:23.000Z",
        "description": "",
        "id": "2762638401",
        "location": "Japan",
        "name": "烤蘑菇串儿",
        "profile_image_url": "https://pbs.twimg.com/profile_images/1950588241733992448/tWJSkEHh_normal.jpg",
        "protected": false,
        "public_metrics": {
          "followers_count": 0,
          "following_count": 42,
          "tweet_count": 8,
          "listed_count": 0,
          "like_count": 39,
          "media_count": 1
        },
        "username": "Jessie_Tianjia",
        "verified": false
      },
      {
        "created_at": "2025-10-30T02:48:11.000Z",
        "description": "我是Cu，可以叫我小铜，建造一个和G的小角落…(＞＜;) 帖子里的画都由本人纯手工绘制… NSFW/r18g内容请注意避雷 我很恶俗，非常之恶俗，创到你的话…是你非要看的🥹",
        "id": "1983727547142828035",
        "name": "Cu",
        "pinned_tweet_id": "1994957222217187503",
        "profile_image_url": "https://pbs.twimg.com/profile_images/2012711336229093376/OLp7LP_s_normal.jpg",
        "protected": false,
        "public_metrics": {
          "followers_count": 2209,
          "following_count": 203,
          "tweet_count": 2314,
          "listed_count": 2,
          "like_count": 808,
          "media_count": 176
        },
        "username": "copper1234000",
        "verified": true
      }
    ],
    "tweets": [
      {
        "article": {},
        "attachments": {},
        "author_id": "1741993395910811648",
        "conversation_id": "2017353644375474297",
        "created_at": "2026-01-31T09:58:43.000Z",
        "edit_controls": {
          "edits_remaining": 5,
          "is_edit_eligible": false,
          "editable_until": "2026-01-31T10:58:43.000Z"
        },
        "edit_history_tweet_ids": [
          "2017538021843997118"
        ],
        "entities": {
          "mentions": [
            {
              "start": 0,
              "end": 15,
              "username": "Jessie_Tianjia",
              "id": "2762638401"
            },
            {
              "start": 16,
              "end": 30,
              "username": "copper1234000",
              "id": "1983727547142828035"
            }
          ]
        },
        "geo": {},
        "id": "2017538021843997118",
        "in_reply_to_user_id": "2762638401",
        "lang": "zh",
        "note_tweet": {
          "entities": {}
        },
        "possibly_sensitive": false,
        "public_metrics": {
          "retweet_count": 0,
          "reply_count": 0,
          "like_count": 0,
          "quote_count": 0,
          "bookmark_count": 0,
          "impression_count": 0
        },
        "referenced_tweets": [
          {
            "type": "replied_to",
            "id": "2017378723448631405"
          }
        ],
        "reply_settings": "everyone",
        "text": "@Jessie_Tianjia @copper1234000 啊它开车还需要提示词吗（）"
      },
      {
        "article": {},
        "attachments": {},
        "author_id": "2762638401",
        "conversation_id": "2017353644375474297",
        "created_at": "2026-01-30T23:25:43.000Z",
        "edit_controls": {
          "edits_remaining": 5,
          "is_edit_eligible": false,
          "editable_until": "2026-01-31T00:25:43.000Z"
        },
        "edit_history_tweet_ids": [
          "2017378723448631405"
        ],
        "entities": {
          "mentions": [
            {
              "start": 0,
              "end": 14,
              "username": "copper1234000",
              "id": "1983727547142828035"
            }
          ]
        },
        "geo": {},
        "id": "2017378723448631405",
        "in_reply_to_user_id": "1983727547142828035",
        "lang": "zh",
        "note_tweet": {
          "entities": {}
        },
        "possibly_sensitive": false,
        "public_metrics": {
          "retweet_count": 0,
          "reply_count": 1,
          "like_count": 0,
          "quote_count": 0,
          "bookmark_count": 0,
          "impression_count": 131
        },
        "referenced_tweets": [
          {
            "type": "replied_to",
            "id": "2017353644375474297"
          }
        ],
        "reply_settings": "everyone",
        "text": "@copper1234000 铜老师，可以请教gemini怎么破甲以及开车吗"
      }
    ]
  },
  "_pale_fire": {
    "x_api_reply_chains": {
      "2017353644375474297": {
        "version": 1,
        "fetched_at": "2026-04-18T01:26:44Z",
        "max_depth": 63,
        "posts": [
          {
            "id": "2017353644375474297",
            "source": "x_api_oauth1",
            "payload": {
              "data": {
                "text": "心情 https://t.co/RSgQqnT4Wi",
                "reply_settings": "everyone",
                "context_annotations": [
                  {
                    "domain": {
                      "id": "46",
                      "name": "Business Taxonomy",
                      "description": "Categories within Brand Verticals that narrow down the scope of Brands"
                    },
                    "entity": {
                      "id": "1557696940178935808",
                      "name": "Gaming Business",
                      "description": "Brands, companies, advertisers and every non-person handle with the profit intent related to offline and online games such as gaming consoles, tabletop games, video game publishers"
                    }
                  }
                ],
                "edit_history_tweet_ids": [
                  "2017353644375474297"
                ],
                "attachments": {
                  "media_keys": [
                    "3_2017353640520937472"
                  ]
                },
                "public_metrics": {
                  "retweet_count": 5,
                  "reply_count": 3,
                  "like_count": 102,
                  "quote_count": 3,
                  "bookmark_count": 2,
                  "impression_count": 4418
                },
                "created_at": "2026-01-30T21:46:04.000Z",
                "possibly_sensitive": false,
                "author_id": "1983727547142828035",
                "edit_controls": {
                  "edits_remaining": 5,
                  "is_edit_eligible": true,
                  "editable_until": "2026-01-30T22:46:04.000Z"
                },
                "lang": "ja",
                "conversation_id": "2017353644375474297",
                "entities": {
                  "urls": [
                    {
                      "start": 3,
                      "end": 26,
                      "url": "https://t.co/RSgQqnT4Wi",
                      "expanded_url": "https://x.com/copper1234000/status/2017353644375474297/photo/1",
                      "display_url": "pic.x.com/RSgQqnT4Wi",
                      "media_key": "3_2017353640520937472"
                    }
                  ]
                },
                "id": "2017353644375474297"
              },
              "includes": {
                "media": [
                  {
                    "height": 852,
                    "width": 1074,
                    "media_key": "3_2017353640520937472",
                    "url": "https://pbs.twimg.com/media/G_8UcpmXcAAgEnD.jpg",
                    "type": "photo"
                  }
                ],
                "users": [
                  {
                    "name": "Cu",
                    "verified": false,
                    "profile_image_url": "https://pbs.twimg.com/profile_images/2029403852902912000/MvRb_FES_normal.jpg",
                    "username": "copper1234000",
                    "protected": false,
                    "created_at": "2025-10-30T02:48:11.000Z",
                    "id": "1983727547142828035",
                    "public_metrics": {
                      "followers_count": 3417,
                      "following_count": 326,
                      "tweet_count": 4510,
                      "listed_count": 3,
                      "like_count": 1927,
                      "media_count": 317
                    },
                    "description": "我是Cu，可以叫我小铜，这里是囤积我和两只机日常的小角落…(＞＜;) 帖子里的画都由本人纯手工绘制… NSFW/r18g内容请注意避雷 我很恶俗，非常之恶俗，创到你的话…是你非要看的🥹"
                  }
                ]
              }
            }
          }
        ]
      }
    }
  }
}
